README.md
setup.py
apiql/__init__.py
apiql/criteria.py
apiql/parser.py
apiql.egg-info/PKG-INFO
apiql.egg-info/SOURCES.txt
apiql.egg-info/dependency_links.txt
apiql.egg-info/requires.txt
apiql.egg-info/top_level.txt
apiql/backends/__init__.py
apiql/backends/sqlalchemy/__init__.py
apiql/backends/sqlalchemy/orm/__init__.py
apiql/backends/sqlalchemy/orm/expression.py
apiql/backends/sqlalchemy/orm/query.py
apiql/backends/sqlalchemy/orm/whitelist.py
apiql/grammar/ApiQL.interp
apiql/grammar/ApiQL.tokens
apiql/grammar/ApiQLLexer.interp
apiql/grammar/ApiQLLexer.py
apiql/grammar/ApiQLLexer.tokens
apiql/grammar/ApiQLParser.py
apiql/grammar/ApiQLVisitor.py
apiql/grammar/__init__.py
apiql/grammar/transformer.py
tests/__init__.py
tests/test_parser.py
tests/test_query.py
tests/backends/__init__.py
tests/backends/sqlalchemy_fixtures.py
tests/backends/test_sqlalchemy.py
tests/backends/test_whitelist.py