Metadata-Version: 2.1
Name: apiql
Version: 0.12.6
Summary: A simple API Query Language
Home-page: https://github.com/karaznie/apiql
Author: Artur Karazniewicz
Author-email: karaznie+pip@protonmail.com
License: UNKNOWN
Project-URL: Homepage, https://github.com/akarazniewicz/apiql
Project-URL: Bug Tracker, https://github.com/akarazniewicz/apiql/issues
Project-URL: Documentation, https://github.com/akarazniewicz/apiql
Project-URL: Source Code, https://github.com/akarazniewicz/apiql
Keywords: api dynamic query flask bottle django sqlalchemy
Platform: UNKNOWN
Classifier: Programming Language :: Python :: 3.5
Classifier: Programming Language :: Python :: 3.6
Classifier: Programming Language :: Python :: 3.7
Classifier: Development Status :: 4 - Beta
Classifier: License :: OSI Approved :: MIT License
Classifier: Operating System :: OS Independent
Classifier: Topic :: Software Development :: Libraries :: Python Modules
Classifier: Intended Audience :: Developers
Classifier: Environment :: Web Environment
Requires-Python: >=3.5
